{"arg":{"eur":{"value":261.4,"extras":{"buy":251.75,"sell":271.05,"average":261.4}},"usd":{"value":241.03,"extras":{"buy":234.31,"sell":247.75,"average":241.03}},"usdCcl":{"value":480.99,"extras":{"buy":479.17,"sell":482.81,"average":480.99}},"usdMep":{"value":468.21,"extras":{"buy":468.72,"sell":467.7,"average":468.21}},"usdBlue":{"value":489.5,"extras":{"buy":487,"sell":492,"average":489.5}}},"all":{"aed":{"value":3.672907},"afn":{"value":88.000151},"all":{"value":102.669804},"amd":{"value":386.52049},"ang":{"value":1.80194},"aoa":{"value":565.001123},"ars":{"value":238.839272},"aud":{"value":1.534298},"awg":{"value":1.800003},"azn":{"value":1.700002},"bam":{"value":1.822055},"bbd":{"value":2.018644},"bdt":{"value":107.26526},"bgn":{"value":1.822318},"bhd":{"value":0.377015},"bif":{"value":2820.004438},"bmd":{"value":1.000001},"bnd":{"value":1.351321},"bob":{"value":6.909574},"brl":{"value":5.036308},"bsd":{"value":0.99982},"btn":{"value":82.676533},"bwp":{"value":13.771276},"byn":{"value":2.523586},"byr":{"value":19600},"bzd":{"value":2.015291},"cad":{"value":1.360037},"cdf":{"value":2335.003439},"chf":{"value":0.906001},"clf":{"value":0.029169},"clp":{"value":804.851223},"cny":{"value":7.08001},"cop":{"value":4393.006135},"crc":{"value":540.622109},"cuc":{"value":1.004955},"cup":{"value":23.994701},"cve":{"value":103.300109},"czk":{"value":22.083044},"djf":{"value":177.720338},"dkk":{"value":6.939907},"dop":{"value":54.450099},"dzd":{"value":136.738236},"egp":{"value":30.80145},"ern":{"value":15.000023},"etb":{"value":54.592553},"eur":{"value":0.931852},"fjd":{"value":2.248754},"fkp":{"value":0.805723},"gbp":{"value":0.805716},"gel":{"value":2.595003},"ggp":{"value":0.805723},"ghs":{"value":11.450016},"gip":{"value":0.805723},"gmd":{"value":59.550075},"gnf":{"value":8650.01011},"gtq":{"value":7.818563},"gyd":{"value":211.476027},"hkd":{"value":7.834203},"hnl":{"value":24.577892},"hrk":{"value":7.021035},"htg":{"value":140.795146},"huf":{"value":345.050441},"idr":{"value":14986.029076},"ils":{"value":3.707245},"imp":{"value":0.805723},"inr":{"value":82.684252},"iqd":{"value":1310.001429},"irr":{"value":42325.079545},"isk":{"value":139.12025},"jep":{"value":0.805723},"jmd":{"value":153.857845},"jod":{"value":0.709501},"jpy":{"value":139.796145},"kes":{"value":138.500257},"kgs":{"value":87.590152},"khr":{"value":4116.004606},"kmf":{"value":459.450889},"kpw":{"value":899.967094},"krw":{"value":1320.117197},"kwd":{"value":0.307501},"kyd":{"value":0.833152},"kzt":{"value":447.366398},"lak":{"value":17760.035297},"lbp":{"value":15057.404023},"lkr":{"value":293.968851},"lrd":{"value":168.375306},"lsl":{"value":19.710027},"ltl":{"value":2.95274},"lvl":{"value":0.60489},"lyd":{"value":4.825008},"mad":{"value":10.172512},"mdl":{"value":17.806978},"mga":{"value":4405.777233},"mkd":{"value":57.309547},"mmk":{"value":2099.60228},"mnt":{"value":3473.628099},"mop":{"value":8.066667},"mro":{"value":34.300051},"mur":{"value":45.584643},"mvr":{"value":15.31003},"mwk":{"value":1026.501094},"mxn":{"value":17.670734},"myr":{"value":4.601507},"mzn":{"value":63.250075},"nad":{"value":19.710038},"ngn":{"value":462.000903},"nio":{"value":36.565606},"nok":{"value":11.184716},"npr":{"value":132.28475},"nzd":{"value":1.653978},"omr":{"value":0.385028},"pab":{"value":0.99982},"pen":{"value":3.672506},"pgk":{"value":3.594376},"php":{"value":56.400058},"pkr":{"value":285.825364},"pln":{"value":4.227355},"pyg":{"value":7213.571371},"qar":{"value":3.640504},"ron":{"value":4.628409},"rsd":{"value":109.255128},"rub":{"value":79.645149},"rwf":{"value":1135.001771},"sar":{"value":3.749924},"sbd":{"value":8.333928},"scr":{"value":13.128413},"sdg":{"value":601.000784},"sek":{"value":10.866779},"sgd":{"value":1.350867},"shp":{"value":1.216752},"sll":{"value":19750.03774},"sos":{"value":568.500866},"srd":{"value":37.416549},"std":{"value":20697.981008},"svc":{"value":8.747796},"syp":{"value":2512.533189},"szl":{"value":19.710034},"thb":{"value":34.710045},"tjs":{"value":10.922745},"tmt":{"value":3.500006},"tnd":{"value":3.088754},"top":{"value":2.379704},"try":{"value":20.616633},"ttd":{"value":6.788875},"twd":{"value":30.576331},"tzs":{"value":2365.00404},"uah":{"value":36.925737},"ugx":{"value":3764.66026},"usd":{"value":1},"uyu":{"value":38.839437},"uzs":{"value":11402.876175},"vef":{"value":2622189.725154},"vnd":{"value":23485.037136},"vuv":{"value":120.707268},"wst":{"value":2.740446},"xaf":{"value":611.105761},"xag":{"value":0.043098},"xau":{"value":0.00051},"xcd":{"value":2.702553},"xdr":{"value":0.750796},"xof":{"value":613.501144},"xpf":{"value":111.825214},"yer":{"value":250.300274},"zar":{"value":19.687792},"zmk":{"value":9001.2},"zmw":{"value":19.372714},"zwl":{"value":321.999592}},"updatedAt":1685559604972}